generated_rtl/register_file.v
module reg_file (
    input clk,
    input rst,
    input we,
    input [4:0] rs1, rs2, rd,
    input [31:0] wdata,
    output [31:0] rdata1, rdata2
);
    reg [31:0] regs [0:31];
    assign rdata1 = (rs1 == 5'b0) ? 32'b0 : regs[rs1];
    assign rdata2 = (rs2 == 5'b0) ? 32'b0 : regs[rs2];
    always @(posedge clk or posedge rst) begin
        if (rst) begin
            for (int i = 1; i < 32; i++) begin
                regs[i] <= 32'b0;
            end
        end else if (we && rd != 5'b0) begin
            regs[rd] <= wdata;
        end
    end
endmodule

sim/wave_regfile.vcd
$version Generated by VerilatedVcd $end
$timescale 1ps $end
 $scope module TOP $end
  $var wire 1 D clk $end
  $var wire 1 E rst $end
  $var wire 1 F we $end
  $var wire 5 G rs1 [4:0] $end
  $var wire 5 H rs2 [4:0] $end
  $var wire 5 I rd [4:0] $end
  $var wire 32 J wdata [31:0] $end
  $var wire 32 K rdata1 [31:0] $end
  $var wire 32 L rdata2 [31:0] $end
  $scope module reg_file $end
   $var wire 1 D clk $end
   $var wire 1 E rst $end
   $var wire 1 F we $end
   $var wire 5 G rs1 [4:0] $end
   $var wire 5 H rs2 [4:0] $end
   $var wire 5 I rd [4:0] $end
   $var wire 32 J wdata [31:0] $end
   $var wire 32 K rdata1 [31:0] $end
   $var wire 32 L rdata2 [31:0] $end
   $var wire 32 # regs[0] [31:0] $end
   $var wire 32 $ regs[1] [31:0] $end
   $var wire 32 % regs[2] [31:0] $end
   $var wire 32 & regs[3] [31:0] $end
   $var wire 32 ' regs[4] [31:0] $end
   $var wire 32 ( regs[5] [31:0] $end
   $var wire 32 ) regs[6] [31:0] $end
   $var wire 32 * regs[7] [31:0] $end
   $var wire 32 + regs[8] [31:0] $end
   $var wire 32 , regs[9] [31:0] $end
   $var wire 32 - regs[10] [31:0] $end
   $var wire 32 . regs[11] [31:0] $end
   $var wire 32 / regs[12] [31:0] $end
   $var wire 32 0 regs[13] [31:0] $end
   $var wire 32 1 regs[14] [31:0] $end
   $var wire 32 2 regs[15] [31:0] $end
   $var wire 32 3 regs[16] [31:0] $end
   $var wire 32 4 regs[17] [31:0] $end
   $var wire 32 5 regs[18] [31:0] $end
   $var wire 32 6 regs[19] [31:0] $end
   $var wire 32 7 regs[20] [31:0] $end
   $var wire 32 8 regs[21] [31:0] $end
   $var wire 32 9 regs[22] [31:0] $end
   $var wire 32 : regs[23] [31:0] $end
   $var wire 32 ; regs[24] [31:0] $end
   $var wire 32 < regs[25] [31:0] $end
   $var wire 32 = regs[26] [31:0] $end
   $var wire 32 > regs[27] [31:0] $end
   $var wire 32 ? regs[28] [31:0] $end
   $var wire 32 @ regs[29] [31:0] $end
   $var wire 32 A regs[30] [31:0] $end
   $var wire 32 B regs[31] [31:0] $end
   $scope module unnamedblk1 $end
    $var wire 32 C i [31:0] $end
   $upscope $end
  $upscope $end
 $upscope $end
$enddefinitions $end


#0
b00000000000000000000000000000000 #
b00000000000000000000000000000000 $
b00000000000000000000000000000000 %
b00000000000000000000000000000000 &
b00000000000000000000000000000000 '
b00000000000000000000000000000000 (
b00000000000000000000000000000000 )
b00000000000000000000000000000000 *
b00000000000000000000000000000000 +
b00000000000000000000000000000000 ,
b00000000000000000000000000000000 -
b00000000000000000000000000000000 .
b00000000000000000000000000000000 /
b00000000000000000000000000000000 0
b00000000000000000000000000000000 1
b00000000000000000000000000000000 2
b00000000000000000000000000000000 3
b00000000000000000000000000000000 4
b00000000000000000000000000000000 5
b00000000000000000000000000000000 6
b00000000000000000000000000000000 7
b00000000000000000000000000000000 8
b00000000000000000000000000000000 9
b00000000000000000000000000000000 :
b00000000000000000000000000000000 ;
b00000000000000000000000000000000 <
b00000000000000000000000000000000 =
b00000000000000000000000000000000 >
b00000000000000000000000000000000 ?
b00000000000000000000000000000000 @
b00000000000000000000000000000000 A
b00000000000000000000000000000000 B
b00000000000000000000000000000000 C
0D
1E
0F
b00000 G
b00000 H
b00000 I
b00000000000000000000000000000000 J
b00000000000000000000000000000000 K
b00000000000000000000000000000000 L
#1
b00000000000000000000000000100000 C
1D
#2
0D
0E
1F
b11011110101011011011111011101111 J
#3
1D
#4
0D
b00001 I
b10101011110011010001001000110100 J
#5
b10101011110011010001001000110100 $
1D
#6
0D
b00001 G
b00010 I
b00010010001101000101011001111000 J
b10101011110011010001001000110100 K
#7
b00010010001101000101011001111000 %
1D
#8
0D
b00010 H
b11111 I
b11111111111111111111111111111111 J
b00010010001101000101011001111000 L
#9
b11111111111111111111111111111111 B
1D
#10
0D
0F
b11111 G
b00001 I
b00000000000000000000000000000000 J
b11111111111111111111111111111111 K
