generated_rtl/pc.v
module program_counter(
    input  clk,
    input  rst,
    input  stall,
    input  branch_taken,
    input  [31:0] branch_target,
    input  jump_taken,
    input  [31:0] jump_target,
    output [31:0] pc,
    output [31:0] next_pc
);

reg [31:0] pc_reg;

always @(posedge clk or posedge rst) begin
    if (rst) begin
        pc_reg <= 32'd0;
    end else if (stall) begin
        pc_reg <= pc_reg;
    end else if (branch_taken) begin
        pc_reg <= branch_target;
    end else if (jump_taken) begin
        pc_reg <= jump_target;
    end else begin
        pc_reg <= pc_reg + 32'd4;
    end
end

assign pc = pc_reg;
assign next_pc = pc_reg + 32'd4;

endmodule

sim/wave_pc.vcd
$version Generated by VerilatedVcd $end
$timescale 1ps $end
 $scope module TOP $end
  $var wire 1 # clk $end
  $var wire 1 $ rst $end
  $var wire 1 % stall $end
  $var wire 1 & branch_taken $end
  $var wire 32 ' branch_target [31:0] $end
  $var wire 1 ( jump_taken $end
  $var wire 32 ) jump_target [31:0] $end
  $var wire 32 * pc [31:0] $end
  $var wire 32 + next_pc [31:0] $end
  $scope module program_counter $end
   $var wire 1 # clk $end
   $var wire 1 $ rst $end
   $var wire 1 % stall $end
   $var wire 1 & branch_taken $end
   $var wire 32 ' branch_target [31:0] $end
   $var wire 1 ( jump_taken $end
   $var wire 32 ) jump_target [31:0] $end
   $var wire 32 * pc [31:0] $end
   $var wire 32 + next_pc [31:0] $end
   $var wire 32 , pc_reg [31:0] $end
  $upscope $end
 $upscope $end
$enddefinitions $end


#0
0#
1$
0%
0&
b00000000000000000000000000000000 '
0(
b00000000000000000000000000000000 )
b00000000000000000000000000000000 *
b00000000000000000000000000000100 +
b00000000000000000000000000000000 ,
#1
1#
#2
0#
0$
#3
1#
b00000000000000000000000000000100 *
b00000000000000000000000000001000 +
b00000000000000000000000000000100 ,
#4
0#
#5
1#
b00000000000000000000000000001000 *
b00000000000000000000000000001100 +
b00000000000000000000000000001000 ,
#6
0#
1&
b00000000000000000000000100000000 '
#7
1#
b00000000000000000000000100000000 *
b00000000000000000000000100000100 +
b00000000000000000000000100000000 ,
#8
0#
0&
#9
1#
b00000000000000000000000100000100 *
b00000000000000000000000100001000 +
b00000000000000000000000100000100 ,
#10
0#
1(
b00000000000000000000001000000000 )
#11
1#
b00000000000000000000001000000000 *
b00000000000000000000001000000100 +
b00000000000000000000001000000000 ,
#12
0#
0(
#13
1#
b00000000000000000000001000000100 *
b00000000000000000000001000001000 +
b00000000000000000000001000000100 ,
#14
0#
1%
#15
1#
#16
0#
0%
#17
1#
b00000000000000000000001000001000 *
b00000000000000000000001000001100 +
b00000000000000000000001000001000 ,
