generated_rtl/alu.v
module alu (
    input [31:0] a,
    input [31:0] b,
    input [3:0] alu_op,
    output reg [31:0] result,
    output reg zero
);

    always @(*) begin
        case (alu_op)
            4'b0000: result = a + b;           // ADD
            4'b0001: result = a - b;           // SUB
            4'b0010: result = a & b;           // AND
            4'b0011: result = a | b;           // OR
            4'b0100: result = a ^ b;           // XOR
            4'b0101: result = a << b[4:0];     // SLL
            4'b0110: result = a >> b[4:0];     // SRL
            4'b0111: result = $signed(a) >>> b[4:0]; // SRA
            4'b1000: result = ($signed(a) < $signed(b)) ? 1 : 0; // SLT
            4'b1001: result = (a < b) ? 1 : 0; // SLTU
            default: result = 32'b0;
        endcase

        zero = (result == 32'b0);
    end

endmodule

sim/wave.vcd
$version Generated by VerilatedVcd $end
$timescale 1ps $end
 $scope module TOP $end
  $var wire 32 # a [31:0] $end
  $var wire 32 $ b [31:0] $end
  $var wire 4 % alu_op [3:0] $end
  $var wire 32 & result [31:0] $end
  $var wire 1 ' zero $end
  $scope module alu $end
   $var wire 32 # a [31:0] $end
   $var wire 32 $ b [31:0] $end
   $var wire 4 % alu_op [3:0] $end
   $var wire 32 & result [31:0] $end
   $var wire 1 ' zero $end
  $upscope $end
 $upscope $end
$enddefinitions $end


#0
b00000000000000000000000000001010 #
b00000000000000000000000000000101 $
b0000 %
b00000000000000000000000000001111 &
0'
#1
b0001 %
b00000000000000000000000000000101 &
#2
b00000000000000000000000011111111 #
b00000000000000000000000000001111 $
b0010 %
b00000000000000000000000000001111 &
#3
b00000000000000000000000011110000 #
b0011 %
b00000000000000000000000011111111 &
#4
b00000000000000000000000011111111 #
b00000000000000000000000011111111 $
b0100 %
b00000000000000000000000000000000 &
1'
#5
b00000000000000000000000000000001 #
b00000000000000000000000000000100 $
b0101 %
b00000000000000000000000000010000 &
0'
#6
b00000000000000000000000000010000 #
b0110 %
b00000000000000000000000000000001 &
#7
b11111111111111111111111111111111 #
b0111 %
b11111111111111111111111111111111 &
#8
b00000000000000000000000000000001 $
b1000 %
b00000000000000000000000000000001 &
#9
b00000000000000000000000000000001 #
b11111111111111111111111111111111 $
b1001 %
#10
b00000000000000000000000000000101 #
b00000000000000000000000000000101 $
b0001 %
b00000000000000000000000000000000 &
1'
