generated_rtl/pipeline_top.v
module riscv_pipeline (
    input clk,
    input rst,
 
    output [31:0] instr_mem_addr,
    input  [31:0] instr_mem_data,
 
    output reg        data_mem_we,
    output reg        data_mem_re,
    output reg [31:0] data_mem_addr,
    output reg [31:0] data_mem_wdata,
    input      [31:0] data_mem_rdata
);
 
    reg [31:0] pc;
    assign instr_mem_addr = pc;

    always @(posedge clk) begin
        if (rst) pc <= 0;
        else     pc <= pc + 4;
    end
 
    reg [31:0] if_id_instr;
    always @(posedge clk) begin
        if (rst) if_id_instr <= 32'h00000013;
        else     if_id_instr <= instr_mem_data;
    end
 
    wire [6:0] opcode = if_id_instr[6:0];
    wire [2:0] funct3 = if_id_instr[14:12];
    wire [4:0] rs1    = if_id_instr[19:15];
    wire [4:0] rs2    = if_id_instr[24:20];
    wire [4:0] rd     = if_id_instr[11:7];

    wire [31:0] imm_i = {{20{if_id_instr[31]}}, if_id_instr[31:20]};
    wire [31:0] imm_s = {{20{if_id_instr[31]}}, if_id_instr[31:25], if_id_instr[11:7]};

    reg [31:0] regfile [0:31];
    integer i;
    initial begin
        for (i = 0; i < 32; i = i + 1) regfile[i] = 0;
    end
 
    reg [31:0] id_ex_rs1_data, id_ex_rs2_data, id_ex_imm;
    reg [4:0]  id_ex_rd, id_ex_rs1, id_ex_rs2;
    reg [6:0]  id_ex_opcode;

    always @(posedge clk) begin
        if (rst) begin
            id_ex_opcode   <= 7'h13;
            id_ex_rd       <= 0;
            id_ex_rs1      <= 0;
            id_ex_rs2      <= 0;
            id_ex_rs1_data <= 0;
            id_ex_rs2_data <= 0;
            id_ex_imm      <= 0;
        end else begin
            id_ex_opcode   <= opcode;
            id_ex_rd       <= rd;
            id_ex_rs1      <= rs1;
            id_ex_rs2      <= rs2;
            id_ex_rs1_data <= regfile[rs1];
            id_ex_rs2_data <= regfile[rs2];
            id_ex_imm      <= (opcode == 7'b0100011) ? imm_s : imm_i;
        end
    end
 
    reg [31:0] ex_mem_result;
    reg [31:0] ex_mem_wdata;
    reg [4:0]  ex_mem_rd;
    reg        ex_mem_reg_write;
    reg        ex_mem_mem_re, ex_mem_mem_we;
 
    wire [31:0] mem_wb_final_result;  

    wire [31:0] fwd_a = (ex_mem_reg_write && ex_mem_rd == id_ex_rs1 && ex_mem_rd != 0) ? ex_mem_result :
                         (mem_wb_reg_write && mem_wb_rd == id_ex_rs1 && mem_wb_rd != 0) ? mem_wb_final_result : 
                         id_ex_rs1_data;

    wire [31:0] fwd_b = (ex_mem_reg_write && ex_mem_rd == id_ex_rs2 && ex_mem_rd != 0) ? ex_mem_result :
                         (mem_wb_reg_write && mem_wb_rd == id_ex_rs2 && mem_wb_rd != 0) ? mem_wb_final_result : 
                         id_ex_rs2_data;

    always @(posedge clk) begin
        if (rst) begin
            ex_mem_reg_write <= 0;
            ex_mem_mem_re    <= 0;
            ex_mem_mem_we    <= 0;
            ex_mem_result    <= 0;
            ex_mem_wdata     <= 0;
            ex_mem_rd        <= 0;
        end else begin
            ex_mem_rd        <= id_ex_rd;
            ex_mem_mem_we    <= (id_ex_opcode == 7'b0100011);
            ex_mem_mem_re    <= (id_ex_opcode == 7'b0000011);
            ex_mem_reg_write <= (id_ex_opcode == 7'b0010011 || id_ex_opcode == 7'b0110011 || id_ex_opcode == 7'b0000011);
            
            case (id_ex_opcode)
                7'b0010011: ex_mem_result <= fwd_a + id_ex_imm;
                7'b0110011: ex_mem_result <= fwd_a + fwd_b;
                7'b0100011: begin 
                    ex_mem_result <= fwd_a + id_ex_imm;
                    ex_mem_wdata  <= fwd_b;
                end
                7'b0000011: ex_mem_result <= fwd_a + id_ex_imm;
                default:    ex_mem_result <= 0;
            endcase
        end
    end
 
    reg [31:0] mem_wb_result;
    reg [31:0] mem_wb_rdata;
    reg [4:0]  mem_wb_rd;
    reg        mem_wb_reg_write;
    reg        mem_wb_mem_to_reg;

    always @(*) begin
        data_mem_we    = ex_mem_mem_we;
        data_mem_re    = ex_mem_mem_re;
        data_mem_addr  = ex_mem_result;
        data_mem_wdata = ex_mem_wdata;
    end

    always @(posedge clk) begin
        if (rst) begin
            mem_wb_reg_write <= 0;
            mem_wb_rd         <= 0;
            mem_wb_result     <= 0;
            mem_wb_rdata      <= 0;
            mem_wb_mem_to_reg <= 0;
        end else begin
            mem_wb_rd         <= ex_mem_rd;
            mem_wb_reg_write  <= ex_mem_reg_write;
            mem_wb_result     <= ex_mem_result;
            mem_wb_rdata      <= data_mem_rdata;
            mem_wb_mem_to_reg <= ex_mem_mem_re;
        end
    end
 
    assign mem_wb_final_result = mem_wb_mem_to_reg ? mem_wb_rdata : mem_wb_result;

    always @(posedge clk) begin
        if (!rst && mem_wb_reg_write && mem_wb_rd != 0) begin
            regfile[mem_wb_rd] <= mem_wb_final_result;
        end
    end

endmodule

sim/wave_pipeline.vcd
$version Generated by VerilatedVcd $end
$timescale 1ps $end
 $scope module TOP $end
  $var wire 1 b clk $end
  $var wire 1 c rst $end
  $var wire 32 d instr_mem_addr [31:0] $end
  $var wire 32 e instr_mem_data [31:0] $end
  $var wire 1 f data_mem_we $end
  $var wire 1 g data_mem_re $end
  $var wire 32 h data_mem_addr [31:0] $end
  $var wire 32 i data_mem_wdata [31:0] $end
  $var wire 32 j data_mem_rdata [31:0] $end
  $scope module riscv_pipeline $end
   $var wire 1 b clk $end
   $var wire 1 c rst $end
   $var wire 32 d instr_mem_addr [31:0] $end
   $var wire 32 e instr_mem_data [31:0] $end
   $var wire 1 f data_mem_we $end
   $var wire 1 g data_mem_re $end
   $var wire 32 h data_mem_addr [31:0] $end
   $var wire 32 i data_mem_wdata [31:0] $end
   $var wire 32 j data_mem_rdata [31:0] $end
   $var wire 32 $ pc [31:0] $end
   $var wire 32 % if_id_instr [31:0] $end
   $var wire 7 & opcode [6:0] $end
   $var wire 3 ' funct3 [2:0] $end
   $var wire 5 ( rs1 [4:0] $end
   $var wire 5 ) rs2 [4:0] $end
   $var wire 5 * rd [4:0] $end
   $var wire 32 + imm_i [31:0] $end
   $var wire 32 , imm_s [31:0] $end
   $var wire 32 - regfile[0] [31:0] $end
   $var wire 32 . regfile[1] [31:0] $end
   $var wire 32 / regfile[2] [31:0] $end
   $var wire 32 0 regfile[3] [31:0] $end
   $var wire 32 1 regfile[4] [31:0] $end
   $var wire 32 2 regfile[5] [31:0] $end
   $var wire 32 3 regfile[6] [31:0] $end
   $var wire 32 4 regfile[7] [31:0] $end
   $var wire 32 5 regfile[8] [31:0] $end
   $var wire 32 6 regfile[9] [31:0] $end
   $var wire 32 7 regfile[10] [31:0] $end
   $var wire 32 8 regfile[11] [31:0] $end
   $var wire 32 9 regfile[12] [31:0] $end
   $var wire 32 : regfile[13] [31:0] $end
   $var wire 32 ; regfile[14] [31:0] $end
   $var wire 32 < regfile[15] [31:0] $end
   $var wire 32 = regfile[16] [31:0] $end
   $var wire 32 > regfile[17] [31:0] $end
   $var wire 32 ? regfile[18] [31:0] $end
   $var wire 32 @ regfile[19] [31:0] $end
   $var wire 32 A regfile[20] [31:0] $end
   $var wire 32 B regfile[21] [31:0] $end
   $var wire 32 C regfile[22] [31:0] $end
   $var wire 32 D regfile[23] [31:0] $end
   $var wire 32 E regfile[24] [31:0] $end
   $var wire 32 F regfile[25] [31:0] $end
   $var wire 32 G regfile[26] [31:0] $end
   $var wire 32 H regfile[27] [31:0] $end
   $var wire 32 I regfile[28] [31:0] $end
   $var wire 32 J regfile[29] [31:0] $end
   $var wire 32 K regfile[30] [31:0] $end
   $var wire 32 L regfile[31] [31:0] $end
   $var wire 32 # i [31:0] $end
   $var wire 32 M id_ex_rs1_data [31:0] $end
   $var wire 32 N id_ex_rs2_data [31:0] $end
   $var wire 32 O id_ex_imm [31:0] $end
   $var wire 5 P id_ex_rd [4:0] $end
   $var wire 5 Q id_ex_rs1 [4:0] $end
   $var wire 5 R id_ex_rs2 [4:0] $end
   $var wire 7 S id_ex_opcode [6:0] $end
   $var wire 32 T ex_mem_result [31:0] $end
   $var wire 32 U ex_mem_wdata [31:0] $end
   $var wire 5 V ex_mem_rd [4:0] $end
   $var wire 1 W ex_mem_reg_write $end
   $var wire 1 X ex_mem_mem_re $end
   $var wire 1 Y ex_mem_mem_we $end
   $var wire 32 Z mem_wb_final_result [31:0] $end
   $var wire 32 [ fwd_a [31:0] $end
   $var wire 32 \ fwd_b [31:0] $end
   $var wire 32 ] mem_wb_result [31:0] $end
   $var wire 32 ^ mem_wb_rdata [31:0] $end
   $var wire 5 _ mem_wb_rd [4:0] $end
   $var wire 1 ` mem_wb_reg_write $end
   $var wire 1 a mem_wb_mem_to_reg $end
  $upscope $end
 $upscope $end
$enddefinitions $end


#0
b00000000000000000000000000100000 #
b00000000000000000000000000000000 $
b00000000000000000000000000000000 %
b0000000 &
b000 '
b00000 (
b00000 )
b00000 *
b00000000000000000000000000000000 +
b00000000000000000000000000000000 ,
b00000000000000000000000000000000 -
b00000000000000000000000000000000 .
b00000000000000000000000000000000 /
b00000000000000000000000000000000 0
b00000000000000000000000000000000 1
b00000000000000000000000000000000 2
b00000000000000000000000000000000 3
b00000000000000000000000000000000 4
b00000000000000000000000000000000 5
b00000000000000000000000000000000 6
b00000000000000000000000000000000 7
b00000000000000000000000000000000 8
b00000000000000000000000000000000 9
b00000000000000000000000000000000 :
b00000000000000000000000000000000 ;
b00000000000000000000000000000000 <
b00000000000000000000000000000000 =
b00000000000000000000000000000000 >
b00000000000000000000000000000000 ?
b00000000000000000000000000000000 @
b00000000000000000000000000000000 A
b00000000000000000000000000000000 B
b00000000000000000000000000000000 C
b00000000000000000000000000000000 D
b00000000000000000000000000000000 E
b00000000000000000000000000000000 F
b00000000000000000000000000000000 G
b00000000000000000000000000000000 H
b00000000000000000000000000000000 I
b00000000000000000000000000000000 J
b00000000000000000000000000000000 K
b00000000000000000000000000000000 L
b00000000000000000000000000000000 M
b00000000000000000000000000000000 N
b00000000000000000000000000000000 O
b00000 P
b00000 Q
b00000 R
b0000000 S
b00000000000000000000000000000000 T
b00000000000000000000000000000000 U
b00000 V
0W
0X
0Y
b00000000000000000000000000000000 Z
b00000000000000000000000000000000 [
b00000000000000000000000000000000 \
b00000000000000000000000000000000 ]
b00000000000000000000000000000000 ^
b00000 _
0`
0a
0b
1c
b00000000000000000000000000000000 d
b00000000000000000000000000010011 e
0f
0g
b00000000000000000000000000000000 h
b00000000000000000000000000000000 i
b00000000000000000000000000000000 j
#1
b00000000000000000000000000010011 %
b0010011 &
b0010011 S
1b
#2
0b
#3
1b
#4
0b
0c
b00000000010100000000000010010011 e
#5
b00000000000000000000000000000100 $
b00000000010100000000000010010011 %
b00101 )
b00001 *
b00000000000000000000000000000101 +
b00000000000000000000000000000001 ,
1W
1b
b00000000000000000000000000000100 d
#6
0b
b00000000000000000000000000010011 e
#7
b00000000000000000000000000001000 $
b00000000000000000000000000010011 %
b00000 )
b00000 *
b00000000000000000000000000000000 +
b00000000000000000000000000000000 ,
b00000000000000000000000000000101 O
b00001 P
b00101 R
1`
1b
b00000000000000000000000000001000 d
#8
0b
#9
b00000000000000000000000000001100 $
b00000000000000000000000000000000 O
b00000 P
b00000 R
b00000000000000000000000000000101 T
b00001 V
1b
b00000000000000000000000000001100 d
b00000000000000000000000000000101 h
#10
0b
#11
b00000000000000000000000000010000 $
b00000000000000000000000000000000 T
b00000 V
b00000000000000000000000000000101 Z
b00000000000000000000000000000101 ]
b00001 _
1b
b00000000000000000000000000010000 d
b00000000000000000000000000000000 h
#12
0b
b00000000101000000000000100010011 e
#13
b00000000000000000000000000010100 $
b00000000101000000000000100010011 %
b01010 )
b00010 *
b00000000000000000000000000001010 +
b00000000000000000000000000000010 ,
b00000000000000000000000000000101 .
b00000000000000000000000000000000 Z
b00000000000000000000000000000000 ]
b00000 _
1b
b00000000000000000000000000010100 d
#14
0b
b00000000000000000000000000010011 e
#15
b00000000000000000000000000011000 $
b00000000000000000000000000010011 %
b00000 )
b00000 *
b00000000000000000000000000000000 +
b00000000000000000000000000000000 ,
b00000000000000000000000000001010 O
b00010 P
b01010 R
1b
b00000000000000000000000000011000 d
#16
0b
#17
b00000000000000000000000000011100 $
b00000000000000000000000000000000 O
b00000 P
b00000 R
b00000000000000000000000000001010 T
b00010 V
1b
b00000000000000000000000000011100 d
b00000000000000000000000000001010 h
#18
0b
#19
b00000000000000000000000000100000 $
b00000000000000000000000000000000 T
b00000 V
b00000000000000000000000000001010 Z
b00000000000000000000000000001010 ]
b00010 _
1b
b00000000000000000000000000100000 d
b00000000000000000000000000000000 h
#20
0b
b00000000001000001000000110110011 e
#21
b00000000000000000000000000100100 $
b00000000001000001000000110110011 %
b0110011 &
b00001 (
b00010 )
b00011 *
b00000000000000000000000000000010 +
b00000000000000000000000000000011 ,
b00000000000000000000000000001010 /
b00000000000000000000000000000000 Z
b00000000000000000000000000000000 ]
b00000 _
1b
b00000000000000000000000000100100 d
#22
0b
b00000000000000000000000000010011 e
#23
b00000000000000000000000000101000 $
b00000000000000000000000000010011 %
b0010011 &
b00000 (
b00000 )
b00000 *
b00000000000000000000000000000000 +
b00000000000000000000000000000000 ,
b00000000000000000000000000000101 M
b00000000000000000000000000001010 N
b00000000000000000000000000000010 O
b00011 P
b00001 Q
b00010 R
b0110011 S
b00000000000000000000000000000101 [
b00000000000000000000000000001010 \
1b
b00000000000000000000000000101000 d
#24
0b
#25
b00000000000000000000000000101100 $
b00000000000000000000000000000000 M
b00000000000000000000000000000000 N
b00000000000000000000000000000000 O
b00000 P
b00000 Q
b00000 R
b0010011 S
b00000000000000000000000000001111 T
b00011 V
b00000000000000000000000000000000 [
b00000000000000000000000000000000 \
1b
b00000000000000000000000000101100 d
b00000000000000000000000000001111 h
#26
0b
#27
b00000000000000000000000000110000 $
b00000000000000000000000000000000 T
b00000 V
b00000000000000000000000000001111 Z
b00000000000000000000000000001111 ]
b00011 _
1b
b00000000000000000000000000110000 d
b00000000000000000000000000000000 h
#28
0b
b00000000001100000010000000100011 e
#29
b00000000000000000000000000110100 $
b00000000001100000010000000100011 %
b0100011 &
b010 '
b00011 )
b00000000000000000000000000000011 +
b00000000000000000000000000001111 0
b00000000000000000000000000000000 Z
b00000000000000000000000000000000 ]
b00000 _
1b
b00000000000000000000000000110100 d
#30
0b
b00000000000000000010001000000011 e
#31
b00000000000000000000000000111000 $
b00000000000000000010001000000011 %
b0000011 &
b00000 )
b00100 *
b00000000000000000000000000000000 +
b00000000000000000000000000000100 ,
b00000000000000000000000000001111 N
b00011 R
b0100011 S
b00000000000000000000000000001111 \
1b
b00000000000000000000000000111000 d
#32
0b
b00000000000000000000000000010011 e
#33
b00000000000000000000000000111100 $
b00000000000000000000000000010011 %
b0010011 &
b000 '
b00000 *
b00000000000000000000000000000000 ,
b00000000000000000000000000000000 N
b00100 P
b00000 R
b0000011 S
b00000000000000000000000000001111 U
0W
1Y
b00000000000000000000000000000000 \
1b
b00000000000000000000000000111100 d
1f
b00000000000000000000000000001111 i
#34
0b
#35
b00000000000000000000000001000000 $
b00000 P
b0010011 S
b00100 V
1W
1X
0Y
0`
1b
b00000000000000000000000001000000 d
0f
1g
#36
0b
b00000000000000000000000000001111 j
#37
b00000000000000000000000001000100 $
b00000 V
0X
b00000000000000000000000000001111 Z
b00000000000000000000000000001111 ^
b00100 _
1`
1a
1b
b00000000000000000000000001000100 d
0g
#38
0b
#39
b00000000000000000000000001001000 $
b00000000000000000000000000001111 1
b00000000000000000000000000000000 Z
b00000 _
0a
1b
b00000000000000000000000001001000 d
#40
0b
#41
b00000000000000000000000001001100 $
1b
b00000000000000000000000001001100 d
#42
0b
#43
b00000000000000000000000001010000 $
1b
b00000000000000000000000001010000 d
#44
0b
#45
b00000000000000000000000001010100 $
1b
b00000000000000000000000001010100 d
#46
0b
#47
b00000000000000000000000001011000 $
1b
b00000000000000000000000001011000 d
#48
0b
#49
b00000000000000000000000001011100 $
1b
b00000000000000000000000001011100 d
#50
0b
#51
b00000000000000000000000001100000 $
1b
b00000000000000000000000001100000 d
#52
0b
#53
b00000000000000000000000001100100 $
1b
b00000000000000000000000001100100 d
#54
0b
#55
b00000000000000000000000001101000 $
1b
b00000000000000000000000001101000 d
#56
0b
#57
b00000000000000000000000001101100 $
1b
b00000000000000000000000001101100 d
#58
0b
#59
b00000000000000000000000001110000 $
1b
b00000000000000000000000001110000 d
#60
0b
#61
b00000000000000000000000001110100 $
1b
b00000000000000000000000001110100 d
#62
0b
#63
b00000000000000000000000001111000 $
1b
b00000000000000000000000001111000 d
#64
0b
#65
b00000000000000000000000001111100 $
1b
b00000000000000000000000001111100 d
#66
0b
#67
b00000000000000000000000010000000 $
1b
b00000000000000000000000010000000 d
#68
0b
#69
b00000000000000000000000010000100 $
1b
b00000000000000000000000010000100 d
#70
0b
#71
b00000000000000000000000010001000 $
1b
b00000000000000000000000010001000 d
#72
0b
#73
b00000000000000000000000010001100 $
1b
b00000000000000000000000010001100 d
#74
0b
#75
b00000000000000000000000010010000 $
1b
b00000000000000000000000010010000 d
#76
0b
#77
b00000000000000000000000010010100 $
1b
b00000000000000000000000010010100 d
#78
0b
#79
b00000000000000000000000010011000 $
1b
b00000000000000000000000010011000 d
#80
0b
#81
b00000000000000000000000010011100 $
1b
b00000000000000000000000010011100 d
#82
0b
#83
b00000000000000000000000010100000 $
1b
b00000000000000000000000010100000 d
