generated_rtl/branch_unit.v
module branch_unit(
    input  wire [31:0] rs1_val,
    input  wire [31:0] rs2_val,
    input  wire [2:0]  funct3,
    input  wire        is_branch,
    output reg        branch_taken
);

always @(*) begin
    case (funct3)
        3'b000: branch_taken = (rs1_val == rs2_val);              
        3'b001: branch_taken = (rs1_val != rs2_val);              
        3'b100: branch_taken = ($signed(rs1_val) < $signed(rs2_val)); 
        3'b101: branch_taken = ($signed(rs1_val) >= $signed(rs2_val)); 
        3'b110: branch_taken = (rs1_val < rs2_val);                
        3'b111: branch_taken = (rs1_val >= rs2_val);               
        default: branch_taken = 0;
    endcase
end

endmodule

sim/wave_branch.vcd
$version Generated by VerilatedVcd $end
$timescale 1ps $end
 $scope module TOP $end
  $var wire 32 # rs1_val [31:0] $end
  $var wire 32 $ rs2_val [31:0] $end
  $var wire 3 % funct3 [2:0] $end
  $var wire 1 & is_branch $end
  $var wire 1 ' branch_taken $end
  $scope module branch_unit $end
   $var wire 32 # rs1_val [31:0] $end
   $var wire 32 $ rs2_val [31:0] $end
   $var wire 3 % funct3 [2:0] $end
   $var wire 1 & is_branch $end
   $var wire 1 ' branch_taken $end
  $upscope $end
 $upscope $end
$enddefinitions $end


#0
b00000000000000000000000000000101 #
b00000000000000000000000000000101 $
b000 %
1&
1'
#1
b00000000000000000000000000000110 $
0'
#2
b001 %
1'
#3
b00000000000000000000000000000101 $
0'
#4
b11111111111111111111111111111111 #
b00000000000000000000000000000001 $
b100 %
1'
#5
b00000000000000000000000000000001 #
b11111111111111111111111111111111 $
0'
#6
b101 %
1'
#7
b11111111111111111111111111111111 #
b00000000000000000000000000000001 $
0'
#8
b00000000000000000000000000000001 #
b11111111111111111111111111111111 $
b110 %
1'
#9
b11111111111111111111111111111111 #
b00000000000000000000000000000001 $
0'
#10
b111 %
1'
#11
b00000000000000000000000000000001 #
b11111111111111111111111111111111 $
0'
#12
b00000000000000000000000000000101 #
b00000000000000000000000000000101 $
b000 %
0&
1'
